multipipe/__init__.py
multipipe/multipipe.py
multipipe-0.1.0.dist-info/LICENSE
multipipe-0.1.0.dist-info/METADATA
multipipe-0.1.0.dist-info/WHEEL
multipipe-0.1.0.dist-info/top_level.txt
multipipe-0.1.0.dist-info/RECORD
