Metadata-Version: 2.1
Name: multipipe
Version: 0.1.0
Summary: A Python utility for multiprocessing pipelines
Home-page: https://github.com/AmenRa/unified-io
Author: Elias Bassani
Author-email: elias.bssn@gmail.com
Keywords: pipeline,multiprocessing,multithreading,utils,utilities
Classifier: Programming Language :: Python :: 3
Classifier: License :: OSI Approved :: MIT License
Classifier: Intended Audience :: Science/Research
Classifier: Operating System :: OS Independent
Classifier: Topic :: Text Processing :: General
Requires-Python: >=3.7
License-File: LICENSE
Requires-Dist: multiprocess
